MANIFEST.in
README.rst
setup.py
tastypy/__init__.py
tastypy/_deep_proxy.py
tastypy/exceptions.py
tastypy/file_utils.py
tastypy/json_serializer.py
tastypy/persistent_ordered_dict.py
tastypy/progress_tracker.py
tastypy/shared_pod_example.py
tastypy/shared_progress_tracker.py
tastypy/test.py
tastypy.egg-info/PKG-INFO
tastypy.egg-info/SOURCES.txt
tastypy.egg-info/dependency_links.txt
tastypy.egg-info/requires.txt
tastypy.egg-info/top_level.txt