Metadata-Version: 1.1
Name: tastypy
Version: 0.0.1
Summary: simple python datastructures that transparently persist to disk
Home-page: https://github.com/enewe101/tastypy
Author: Edward Newell
Author-email: edward.newell@gmail.com
License: MIT
Keywords: datastructure database python persistence storage dictionary dict
Platform: UNKNOWN
Classifier: Development Status :: 3 - Alpha
Classifier: Intended Audience :: Developers
Classifier: Topic :: Software Development :: Build Tools
Classifier: License :: OSI Approved :: MIT License
Classifier: Programming Language :: Python :: 2
